{
	"name": "INR Diary",

	"contentRepositoryConnection": {
		"type": "PRISMIC",
		"repositoryId": "https://inrdiary.cdn.prismic.io/api"
	},

	"locationSettings": {
		"locales": ["en_US", "de_DE"],
		"timeZone": "Europe/Brussels"
	},

	"mailSettings": {
		"host": "mail.postale.io",
		"port": 587,
		"username": "info@inrdiary.com",
		"password": "Wa8t4bhaBK@W1qJoZ9!l"
	},

	"forms": [
		{
			"name": "contact",
			"visitorEmail": {
				"subject": "thank-you-for-your-message",
				"contents": "mail/contact-visitor.ftl"
			},
			"managerEmail": {
				"subject": "new-message-for-inr-diary",
				"contents": "mail/contact-owner.ftl"
			}
		}
	],

	"templates": [
		{
			"name": "main",
			"contents": "templates/main.ftl"
		}
	],

	"errorPage": {
		"name": "Error",
		"template": "main",
		"inserts": {
			"body": "pages/error.ftl"
		}
	},

	"pages": [
		{
			"friendlyUrl": "home",
			"name": "Home",
			"template": "main",
			"inserts": {
				"body": "pages/home.ftl"
			}
		}
	]
}